melonly/__init__.py
melonly/async_client.py
melonly/client.py
melonly/exceptions.py
melonly/models.py
melonly_api-1.0.0.dist-info/licenses/LICENSE
melonly_api-1.0.0.dist-info/METADATA
melonly_api-1.0.0.dist-info/WHEEL
melonly_api-1.0.0.dist-info/top_level.txt
melonly_api-1.0.0.dist-info/RECORD
