Metadata-Version: 2.4
Name: melonly-api
Version: 1.0.0
Summary: A Python client library for the Melonly API
Home-page: https://github.com/Melonly-Moderation/py-melonly-client
Author: Melonly API Client
Author-email: Melonly API Client <contact@example.com>
License: MIT
Project-URL: Homepage, https://github.com/yourusername/melonly-api
Project-URL: Documentation, https://melonly-api.readthedocs.io/
Project-URL: Repository, https://github.com/yourusername/melonly-api.git
Project-URL: Bug Tracker, https://github.com/yourusername/melonly-api/issues
Keywords: melonly,api,client,discord,server,management
Classifier: Development Status :: 5 - Production/Stable
Classifier: Intended Audience :: Developers
Classifier: License :: OSI Approved :: MIT License
Classifier: Operating System :: OS Independent
Classifier: Programming Language :: Python :: 3
Classifier: Programming Language :: Python :: 3.7
Classifier: Programming Language :: Python :: 3.8
Classifier: Programming Language :: Python :: 3.9
Classifier: Programming Language :: Python :: 3.10
Classifier: Programming Language :: Python :: 3.11
Classifier: Programming Language :: Python :: 3.12
Classifier: Topic :: Software Development :: Libraries :: Python Modules
Classifier: Topic :: Internet :: WWW/HTTP :: Dynamic Content
Requires-Python: >=3.7
License-File: LICENSE
Requires-Dist: requests>=2.25.0
Requires-Dist: typing-extensions>=4.0.0; python_version < "3.8"
Provides-Extra: dev
Requires-Dist: pytest>=6.0; extra == "dev"
Requires-Dist: pytest-cov>=2.0; extra == "dev"
Requires-Dist: pytest-asyncio>=0.18.0; extra == "dev"
Requires-Dist: black>=21.0; extra == "dev"
Requires-Dist: flake8>=3.8; extra == "dev"
Requires-Dist: mypy>=0.800; extra == "dev"
Requires-Dist: isort>=5.0; extra == "dev"
Provides-Extra: async
Requires-Dist: aiohttp>=3.7.0; extra == "async"
Dynamic: author
Dynamic: home-page
Dynamic: license-file
Dynamic: requires-python
